Workbook

Sheet Dashboard
B4: [ SMARTTEC.DEV · MEAD DATA CENTER · LIVE MODEL — EDIT YELLOW CELLS ON ASSUMPTIONS ]
B5: INVESTOR DASHBOARD
B6: Phase 1A — 8× HGX B200 · 64 GPUs installed, 60 rentable · ~114 kW IT · Mead, Oklahoma
B8: Total CAPEX | C8: =CAPEX!$C$19 -> 4504711 | E8: Equity required | F8: ='5-Year Model'!$C$18 -> 900942.2
B9: Y1 gross revenue | C9: ='5-Year Model'!D10 -> 2384910 | E9: Y1 net operating income | F9: ='5-Year Model'!$D$12 -> 1778010
B10: Y1 operating margin | C10: ='5-Year Model'!$D$12/'5-Year Model'!D10 -> 0.74552499 | E10: Reserved rate (base) | F10: =Assumptions!$C$12 -> 4.5
B11: Flat payback | C11: ='5-Year Model'!C17 -> 2.533569 | E11: Equity payback | F11: ='5-Year Model'!C21 -> 0.82416496
B12: Y1 DSCR (7-yr term) | C12: ='Debt Option'!$C$10 -> 2.5961945 | E12: Y1 DSCR (5-yr stress) | F12: ='Debt Option'!$C$11 -> 2.0039741
B13: Equity MOIC (5-yr) | C13: ='5-Year Model'!C22 -> 3.6713598 | E13: Equity IRR (5-yr) | F13: ='5-Year Model'!$C$23 -> 0.96550219
B15: [ HOW TO USE ]
B16: 1. Edit blue cells on Assumptions and CAPEX. Everything else recalculates.
B17: 2. Debt Option holds the base-case capital structure — it is not optional in this edition.
B18: 3. The reserved rate is a TARGET, not a contracted rate. No capacity is under signed contract.
B20: Prepared July 2026 · Blueprint V4 (audited 24 Jul 2026) · no debt term sheet signed · securities counsel review required before external circulation.

Sheet Assumptions
B2: [ SMARTTEC.DEV · MEAD DATA CENTER · MODEL INPUTS ]
B3: ASSUMPTIONS
B4: Blue text on grey = edit these levers. Everything else is a formula. Phase 1A per DC Blueprint V4 (audited 24 Jul 2026).
B6: [ CAPACITY ]
B7: Reserved GPUs | C7: 48 | D7: Billed 24/7/365 regardless of utilisation. Target rate — NOT yet contracted.
B8: On-demand GPUs | C8: 12 | D8: Balance of the 60 rentable GPUs, sold hourly.
B9: Hours per year | C9: 8760 | D9: 24/7/365
B10: On-demand utilisation | C10: 0.75 | D10: Blueprint V4 base case
B11: [ RATES — YEAR 1 ]
B12: Reserved rate ($/GPU-hr) | C12: 4.5 | D12: Low end of the verified $4.50–$5.50 reserved band. A target, not a signature.
B13: On-demand rate ($/GPU-hr) | C13: 6.25 | D13: At the Jul-2026 independent market median ($6.03 avg / $6.12–6.25 median).
B14: Annual revenue decay | C14: 0.1 | D14: Whole revenue line declines 10%/yr as newer silicon ships.
B15: [ CAPITAL & TERMINAL ]
B16: Total CAPEX | C16: =CAPEX!$C$19 -> 4504711 | D16: Linked live from the CAPEX tab.
B17: Residual hardware value @ Y5 | C17: 0 | D17: Deliberately zero. The previous edition assumed $450K.
B18: Debt share of CAPEX | C18: 0.8 | D18: Senior equipment debt. Balance is equity.
B19: [ ANNUAL OPERATING COSTS ]
B20: Power & cooling | C20: 110000 | D20: 114.4 kW IT full-server draw @ OK ~$0.08/kWh
B21: Fiber — Dobson 100G symmetrical DIA | C21: 96900 | D21: Signed quote: $8,075/mo, 60-month term, install waived
B22: Team — 3 HPC engineers | C22: 360000 | D22: $120K avg, Oklahoma market. Raised from 2 when the build doubled.
B23: Insurance, property tax, software | C23: 40000 | D23: Estimate; includes key-man cover
B24: [ DEBT TERMS ]
B25: Interest rate | C25: 0.085 | D25: Assumed. NO TERM SHEET SIGNED — confirm before relying on this.
B26: Term (years) | C26: 7 | D26: GPU lenders commonly write 3–5 yr paper. See the 5-yr DSCR on Debt Option.

Sheet CAPEX
B2: [ SMARTTEC.DEV · MEAD DATA CENTER ]
B3: CAPEX — PHASE 1A BUILD (BLUEPRINT V4)
B5: Item | C5: Cost | D5: Note
B6: GPU servers — 8× HGX B200 8-GPU (64 GPUs, 60 rentable) | C6: 3160000 | D6: $375K/system + $20K shipping & install each. Formal quote is a Gate-0 item.
B7: InfiniBand fabric — 2× QM9790 NDR, optics, NIC spares | C7: 156440 | D7: Switch carried at $32,500 vs verified $28,443 reseller floor — conservative.
B8: 300 TB NVMe all-flash storage | C8: 120000 | D8: Perishable: NAND +70–75% QoQ in Q2-26. Locks at order.
B9: Power — 2× Eaton 93PR 100kW UPS (N+1), transformer, PDUs, z1Power LFP | C9: 227000 | D9: UPS sized for an earlier smaller build — re-sizing against 114.4 kW is a Gate-0 item.
B10: Cooling + fire suppression — 3× 15-ton CRAC, containment | C10: 121000 | D10: 45 tons installed; only 30T with one unit failed, below the 114.4 kW load. Open item.
B11: Racks, PDUs, structured cabling | C11: 36500 | D11: 9× 48U racks, switched 3-phase PDUs
B12: Management network — switch, firewall, OOB | C12: 7700 | D12: Out-of-band management + tenant isolation
B13: Fiber cross-connect + termination | C13: 5500 | D13: Dobson entry
B14: Soft costs — permitting, legal, PM, AURA dashboard | C14: 83000 | D14: Includes $40K AURA monitoring build
B16: Subtotal | C16: =SUM(C6:C15) -> 3917140
B17: Contingency % | C17: 0.15
B18: Contingency $ | C18: =ROUND(C16*C17,0) -> 587571
B19: TOTAL CAPEX | C19: =C16+C18 -> 4504711 | D19: Blueprint V4 total: $4,504,711

Sheet 5-Year Model
B2: [ SMARTTEC.DEV · MEAD DATA CENTER · BASE CASE — RATES MODELED FALLING ]
B3: FIVE-YEAR MODEL
C5: Year 0 | D5: Year 1 | E5: Year 2 | F5: Year 3 | G5: Year 4 | H5: Year 5
B6: Reserved rate ($/GPU-hr) — display | D6: =Assumptions!$C$12 -> 4.5 | E6: =ROUND(D6*(1-Assumptions!$C$14),2) -> 4.05 | F6: =ROUND(E6*(1-Assumptions!$C$14),2) -> 3.65 | G6: =ROUND(F6*(1-Assumptions!$C$14),2) -> 3.29 | H6: =ROUND(G6*(1-Assumptions!$C$14),2) -> 2.96
B7: On-demand rate ($/GPU-hr) — display | D7: =Assumptions!$C$13 -> 6.25 | E7: =ROUND(D7*(1-Assumptions!$C$14),2) -> 5.63 | F7: =ROUND(E7*(1-Assumptions!$C$14),2) -> 5.07 | G7: =ROUND(F7*(1-Assumptions!$C$14),2) -> 4.56 | H7: =ROUND(G7*(1-Assumptions!$C$14),2) -> 4.1
B8: Reserved revenue | D8: =Assumptions!$C$7*D6*Assumptions!$C$9 -> 1892160 | E8: =D8*(1-Assumptions!$C$14) -> 1702944 | F8: =E8*(1-Assumptions!$C$14) -> 1532649.6 | G8: =F8*(1-Assumptions!$C$14) -> 1379384.6 | H8: =G8*(1-Assumptions!$C$14) -> 1241446.2
B9: On-demand revenue | D9: =Assumptions!$C$8*D7*Assumptions!$C$9*Assumptions!$C$10 -> 492750 | E9: =D9*(1-Assumptions!$C$14) -> 443475 | F9: =E9*(1-Assumptions!$C$14) -> 399127.5 | G9: =F9*(1-Assumptions!$C$14) -> 359214.75 | H9: =G9*(1-Assumptions!$C$14) -> 323293.28
B10: Gross revenue | D10: =D8+D9 -> 2384910 | E10: =E8+E9 -> 2146419 | F10: =F8+F9 -> 1931777.1 | G10: =G8+G9 -> 1738599.4 | H10: =H8+H9 -> 1564739.5
B11: Operating costs | D11: =Assumptions!$C$20+Assumptions!$C$21+Assumptions!$C$22+Assumptions!$C$23 -> 606900 | E11: =Assumptions!$C$20+Assumptions!$C$21+Assumptions!$C$22+Assumptions!$C$23 -> 606900 | F11: =Assumptions!$C$20+Assumptions!$C$21+Assumptions!$C$22+Assumptions!$C$23 -> 606900 | G11: =Assumptions!$C$20+Assumptions!$C$21+Assumptions!$C$22+Assumptions!$C$23 -> 606900 | H11: =Assumptions!$C$20+Assumptions!$C$21+Assumptions!$C$22+Assumptions!$C$23 -> 606900
B12: Net operating income | D12: =D10-D11 -> 1778010 | E12: =E10-E11 -> 1539519 | F12: =F10-F11 -> 1324877.1 | G12: =G10-G11 -> 1131699.4 | H12: =H10-H11 -> 957839.45
B13: Cumulative cash | D13: =D12 -> 1778010 | E13: =D13+E12 -> 3317529 | F13: =E13+F12 -> 4642406.1 | G13: =F13+G12 -> 5774105.5 | H13: =G13+H12 -> 6731944.9
B14: Equity cash flow (levered) | C14: =-'Debt Option'!$C$8 -> -900942.2 | D14: =D12-'Debt Option'!$C$9 -> 1093157.6 | E14: =E12-'Debt Option'!$C$9 -> 854666.61 | F14: =F12-'Debt Option'!$C$9 -> 640024.71 | G14: =G12-'Debt Option'!$C$9 -> 446847 | H14: =H12-'Debt Option'!$C$9+Assumptions!$C$17 -> 272987.07
B16: [ RETURN METRICS — LINKED LIVE ]
B17: Flat payback (Y1 NOI vs total CAPEX) | C17: =CAPEX!$C$19/D12 -> 2.533569 | D17: All-capital basis, before leverage
B18: Equity required | C18: =CAPEX!$C$19*(1-Assumptions!$C$18) -> 900942.2 | D18: 20% of CAPEX
B19: Senior debt | C19: =CAPEX!$C$19*Assumptions!$C$18 -> 3603768.8 | D19: 80% LTV — no term sheet signed
B20: Levered free cash flow — Year 1 | C20: =D12-'Debt Option'!$C$9 -> 1093157.6 | D20: NOI less annual debt service
B21: Equity payback (levered) | C21: =C18/C20 -> 0.82416496 | D21: Highly sensitive to the reserved rate
B22: Equity MOIC (5-yr, incl. residual) | C22: =SUM(D14:H14)/C18 -> 3.6713598 | D22: Residual assumed $0
B23: Equity IRR (5-yr) | C23: =IRR(C14:H14) -> 0.96550219 | D23: Levered. Distributions rank behind debt service.

Sheet Sensitivity
B2: [ SMARTTEC.DEV · WHERE THE ANCHOR RATE LANDS ]
B3: RATE SENSITIVITY — RESERVED RATE
B5: Reserved rate | C5: Y1 NOI | D5: Flat payback | E5: Y1 DSCR (7-yr) | F5: Revenue ÷ opex
B6: 4 | C6: =(Assumptions!$C$7*B6*Assumptions!$C$9+Assumptions!$C$8*Assumptions!$C$13*Assumptions!$C$9*Assumptions!$C$10)-(Assumptions!$C$20+Assumptions!$C$21+Assumptions!$C$22+Assumptions!$C$23) -> 1567770 | D6: =CAPEX!$C$19/C6 -> 2.8733239 | E6: =C6/'Debt Option'!$C$9 -> 2.2892086 | F6: =(Assumptions!$C$7*B6*Assumptions!$C$9+Assumptions!$C$8*Assumptions!$C$13*Assumptions!$C$9*Assumptions!$C$10)/(Assumptions!$C$20+Assumptions!$C$21+Assumptions!$C$22+Assumptions!$C$23) -> 3.5832427
B7: 4.25 | C7: =(Assumptions!$C$7*B7*Assumptions!$C$9+Assumptions!$C$8*Assumptions!$C$13*Assumptions!$C$9*Assumptions!$C$10)-(Assumptions!$C$20+Assumptions!$C$21+Assumptions!$C$22+Assumptions!$C$23) -> 1672890 | D7: =CAPEX!$C$19/C7 -> 2.6927718 | E7: =C7/'Debt Option'!$C$9 -> 2.4427016 | F7: =(Assumptions!$C$7*B7*Assumptions!$C$9+Assumptions!$C$8*Assumptions!$C$13*Assumptions!$C$9*Assumptions!$C$10)/(Assumptions!$C$20+Assumptions!$C$21+Assumptions!$C$22+Assumptions!$C$23) -> 3.7564508
B8: 4.5 | C8: =(Assumptions!$C$7*B8*Assumptions!$C$9+Assumptions!$C$8*Assumptions!$C$13*Assumptions!$C$9*Assumptions!$C$10)-(Assumptions!$C$20+Assumptions!$C$21+Assumptions!$C$22+Assumptions!$C$23) -> 1778010 | D8: =CAPEX!$C$19/C8 -> 2.533569 | E8: =C8/'Debt Option'!$C$9 -> 2.5961945 | F8: =(Assumptions!$C$7*B8*Assumptions!$C$9+Assumptions!$C$8*Assumptions!$C$13*Assumptions!$C$9*Assumptions!$C$10)/(Assumptions!$C$20+Assumptions!$C$21+Assumptions!$C$22+Assumptions!$C$23) -> 3.9296589
B9: 4.75 | C9: =(Assumptions!$C$7*B9*Assumptions!$C$9+Assumptions!$C$8*Assumptions!$C$13*Assumptions!$C$9*Assumptions!$C$10)-(Assumptions!$C$20+Assumptions!$C$21+Assumptions!$C$22+Assumptions!$C$23) -> 1883130 | D9: =CAPEX!$C$19/C9 -> 2.3921402 | E9: =C9/'Debt Option'!$C$9 -> 2.7496874 | F9: =(Assumptions!$C$7*B9*Assumptions!$C$9+Assumptions!$C$8*Assumptions!$C$13*Assumptions!$C$9*Assumptions!$C$10)/(Assumptions!$C$20+Assumptions!$C$21+Assumptions!$C$22+Assumptions!$C$23) -> 4.102867
B10: 5 | C10: =(Assumptions!$C$7*B10*Assumptions!$C$9+Assumptions!$C$8*Assumptions!$C$13*Assumptions!$C$9*Assumptions!$C$10)-(Assumptions!$C$20+Assumptions!$C$21+Assumptions!$C$22+Assumptions!$C$23) -> 1988250 | D10: =CAPEX!$C$19/C10 -> 2.2656663 | E10: =C10/'Debt Option'!$C$9 -> 2.9031804 | F10: =(Assumptions!$C$7*B10*Assumptions!$C$9+Assumptions!$C$8*Assumptions!$C$13*Assumptions!$C$9*Assumptions!$C$10)/(Assumptions!$C$20+Assumptions!$C$21+Assumptions!$C$22+Assumptions!$C$23) -> 4.2760751
B12: All 60 rentable GPUs sold in every row (48 reserved at the row rate + 12 on-demand at the market rate, 75% utilised). The reserved rate is the single most sensitive input in this model and none of it is contracted yet.

Sheet Investment Tiers
B2: [ SMARTTEC.DEV · ILLUSTRATIVE PRO-RATA EQUITY ECONOMICS ]
B3: INVESTMENT TIERS
B5: Tier | C5: Investment | D5: Share of equity | E5: Y1 levered dist. | F5: 5-yr distributions | G5: MOIC | H5: IRR
B6: Pod Partner | C6: 125000 | D6: =C6/'5-Year Model'!$C$18 -> 0.13874364 | E6: =D6*'5-Year Model'!$C$20 -> 151668.67 | F6: =D6*SUM('5-Year Model'!$D$14:$H$14) -> 458919.98 | G6: =F6/C6 -> 3.6713598 | H6: ='5-Year Model'!$C$23 -> 0.96550219
B7: Rack Partner | C7: 250000 | D7: =C7/'5-Year Model'!$C$18 -> 0.27748728 | E7: =D7*'5-Year Model'!$C$20 -> 303337.33 | F7: =D7*SUM('5-Year Model'!$D$14:$H$14) -> 917839.96 | G7: =F7/C7 -> 3.6713598 | H7: ='5-Year Model'!$C$23 -> 0.96550219
B8: Core Partner | C8: 450000 | D8: =C8/'5-Year Model'!$C$18 -> 0.4994771 | E8: =D8*'5-Year Model'!$C$20 -> 546007.2 | F8: =D8*SUM('5-Year Model'!$D$14:$H$14) -> 1652111.9 | G8: =F8/C8 -> 3.6713598 | H8: ='5-Year Model'!$C$23 -> 0.96550219
B9: Site Partner | C9: ='5-Year Model'!$C$18 -> 900942.2 | D9: =C9/'5-Year Model'!$C$18 -> 1 | E9: =D9*'5-Year Model'!$C$20 -> 1093157.6 | F9: =D9*SUM('5-Year Model'!$D$14:$H$14) -> 3307683 | G9: =F9/C9 -> 3.6713598 | H9: ='5-Year Model'!$C$23 -> 0.96550219
B11: IRR is identical across tiers (pro-rata). Figures are levered — they assume the senior debt on the Debt Option tab and are struck after debt service. Equity distributions rank behind the lender in every period.

Sheet Debt Option
B2: [ SMARTTEC.DEV · SENIOR DEBT — THIS IS THE BASE CASE ]
B3: DEBT + EQUITY STRUCTURE
B5: Senior equipment loan | C5: =CAPEX!$C$19*Assumptions!$C$18 -> 3603768.8 | D5: 80% of CAPEX
B6: Interest rate | C6: =Assumptions!$C$25 -> 0.085 | D6: Assumed — no term sheet signed
B7: Term (years) | C7: =Assumptions!$C$26 -> 7 | D7: Lenders commonly write 3–5 yr on GPU collateral
B8: Equity check | C8: =CAPEX!$C$19-C5 -> 900942.2 | D8: Balance of CAPEX
B9: Annual debt service | C9: =-PMT(C6/12,C7*12,C5)*12 -> 684852.39 | D9: Monthly amortisation × 12 — matches Blueprint V4 ($57,071/mo)
B10: Y1 DSCR | C10: ='5-Year Model'!$D$12/C9 -> 2.5961945 | D10: Covenant floors typically sit at 1.25×
B11: Y1 DSCR — if 5-yr paper | C11: ='5-Year Model'!$D$12/(-PMT(C6/12,60,C5)*12) -> 2.0039741 | D11: Stress case. Materially tighter.
B12: Equity cash flows | C12: Year 0 | D12: Year 1 | E12: Year 2 | F12: Year 3 | G12: Year 4 | H12: Year 5
B13: NOI − debt service (+ residual Y5) | C13: =-C8 -> -900942.2 | D13: ='5-Year Model'!D12-$C$9 -> 1093157.6 | E13: ='5-Year Model'!E12-$C$9 -> 854666.61 | F13: ='5-Year Model'!F12-$C$9 -> 640024.71 | G13: ='5-Year Model'!G12-$C$9 -> 446847 | H13: ='5-Year Model'!H12-$C$9+Assumptions!$C$17 -> 272987.07
B15: Y1 equity cash yield | C15: =D13/C8 -> 1.2133493
B16: Equity MOIC (5-yr) | C16: =SUM(D13:H13)/C8 -> 3.6713598
B17: Equity IRR | C17: =IRR(C13:H13) -> 0.96550219
B19: Debt secured by hardware; expect the lender to require a sponsor guarantee. Leverage is what produces the equity returns above — and it is why a shortfall in the reserved rate bites harder here than in an all-equity structure. Debt service is fixed; revenue is not.
